{
    "track_name": "It Could Happen to You",
    "album_name": "Dark Beauty",
    "recording_year": "1974",
    "in_30_corpus": false,
    "bandleader": "Kenny Drew",
    "pianist": "Kenny Drew",
    "channel_overrides": {},
    "mbz_id": "d1070a8a-6190-49f8-a79f-3f661220b98a",
    "notes": "",
    "time_signature": 4,
    "first_downbeat": NaN,
    "rating_bass_audio": NaN,
    "rating_bass_detection": NaN,
    "rating_drums_audio": NaN,
    "rating_drums_detection": NaN,
    "rating_mix": NaN,
    "rating_piano_audio": NaN,
    "rating_piano_detection": NaN,
    "rating_comments": NaN,
    "has_annotations": false,
    "links": {
        "external": [
            "https://www.youtube.com/watch?v=04ClbU83lfQ"
        ]
    },
    "excerpt_duration": "03:00",
    "timestamps": {
        "start": "02:17",
        "end": "05:17"
    },
    "log": [],
    "musicians": {
        "pianist": "Kenny Drew",
        "bassist": "Niels-Henning \u00d8rsted Pedersen",
        "drummer": "Albert \u201cTootie\u201d Heath",
        "leader": "pianist"
    },
    "photos": {
        "musicians": {
            "pianist": null,
            "bassist": null,
            "drummer": null
        },
        "album_artwork": null
    },
    "fname": "drewk-itcouldhappentoyou-rstedntootiea-1974-d1070a8a",
    "tempo": 223.03264234298715,
    "validation": {
        "piano": null,
        "bass": null,
        "drums": null,
        "mix": null
    },
    "stem_silent_perc": {
        "piano": 4.836898278504087e-05,
        "bass": 0.0,
        "drums": 0.0
    }
}